MANIFEST.in
setup.cfg
setup.py
pylastic/__init__.py
pylastic/helpers.py
pylastic.egg-info/PKG-INFO
pylastic.egg-info/SOURCES.txt
pylastic.egg-info/dependency_links.txt
pylastic.egg-info/pbr.json
pylastic.egg-info/requires.txt
pylastic.egg-info/top_level.txt