Metadata-Version: 1.1
Name: pylastic
Version: 0.1.0
Summary: Helper Functions for the Python Elastic Client
Home-page: UNKNOWN
Author: Kyle Amos
Author-email: kylebamos@gmail.com
License: UNKNOWN
Platform: UNKNOWN
Classifier: Development Status :: 3 - Alpha
Classifier: License :: OSI Approved :: GNU General Public License v2 (GPLv2)
Classifier: Programming Language :: Python
Classifier: Programming Language :: Python :: 2.7
Classifier: Programming Language :: Python :: Implementation :: PyPy
Classifier: Topic :: Software Development :: Libraries :: Python Modules
